README.md
setup.cfg
setup.py
thdl/__init__.py
thdl/main.py
thdl.egg-info/PKG-INFO
thdl.egg-info/SOURCES.txt
thdl.egg-info/dependency_links.txt
thdl.egg-info/entry_points.txt
thdl.egg-info/top_level.txt
thdl/check/__init__.py
thdl/check/check.py
thdl/check/file_info.py
thdl/check/reset.py
thdl/generate/__init__.py
thdl/generate/enumeration.py
thdl/generate/generate.py
thdl/generate/record.py
thdl/tests/__init__.py
thdl/tests/check/__init__.py
thdl/tests/check/test_negative_reset.py
thdl/tests/check/test_positive_reset.py
thdl/tests/generate/__init__.py
thdl/tests/generate/test_enumeration.py