Metadata-Version: 2.1
Name: thdl
Version: 0.0.6
Summary: thdl
Home-page: https://github.com/m-kru/thdl
Author: Michał Kruszewski
Author-email: mkru@protonmail.com
License: GPLv3+
Keywords: VHDL,HDL,RTL,FPGA
Platform: UNKNOWN
Classifier: Topic :: Scientific/Engineering :: Electronic Design Automation (EDA)
Classifier: Topic :: Software Development :: Testing
Classifier: Topic :: Software Development :: Quality Assurance
Classifier: Topic :: Utilities
Classifier: Intended Audience :: End Users/Desktop
Classifier: License :: OSI Approved :: GNU General Public License v3 or later (GPLv3+)
